<sequence-cwu id="SEQLST-1">
<publication-reference>
<document-id>
<country>US</country>
<doc-number>07297517</doc-number>
<kind>B2</kind>
<date>20071120</date>
</document-id>
</publication-reference>
<number>1</number>
<sequence-list-new-rules>
<s100>
<s160>30 </s160>
</s100>
<s200>
<s210>1 </s210>
<s211>20 </s211>
<s212>DNA </s212>
<s213>Artificial Sequence </s213>
<s220>
<s223>Oligonucleotide capable of binding specifically 
      to mecA gene or RNA derived from said gene </s223>
</s220>
</s200>
<s400> 1 
ttttttattt tacgatcctg                                                 20 
</s400>
<s200>
<s210>2 </s210>
<s211>20 </s211>
<s212>DNA </s212>
<s213>Artificial Sequence </s213>
<s220>
<s223>Oligonucleotide capable of binding specifically 
      to mecA gene or RNA derived from said gene </s223>
</s220>
</s200>
<s400> 2 
ctcgtttttt atttttagat                                                 20 
</s400>
<s200>
<s210>3 </s210>
<s211>20 </s211>
<s212>DNA </s212>
<s213>Artificial Sequence </s213>
<s220>
<s223>Oligonucleotide capable of binding specifically 
      to mecA gene or RNA derived from said gene </s223>
</s220>
</s200>
<s400> 3 
gtagtttgtt ttaattttat                                                 20 
</s400>
<s200>
<s210>4 </s210>
<s211>20 </s211>
<s212>DNA </s212>
<s213>Artificial Sequence </s213>
<s220>
<s223>Oligonucleotide capable of binding specifically 
      to mecA gene or RNA derived from said gene </s223>
</s220>
</s200>
<s400> 4 
cacataccat cttctttaac                                                 20 
</s400>
<s200>
<s210>5 </s210>
<s211>20 </s211>
<s212>DNA </s212>
<s213>Artificial Sequence </s213>
<s220>
<s223>Oligonucleotide capable of binding specifically 
      to mecA gene or RNA derived from said gene </s223>
</s220>
</s200>
<s400> 5 
tgtttcggtc taaaatttta                                                 20 
</s400>
<s200>
<s210>6 </s210>
<s211>20 </s211>
<s212>DNA </s212>
<s213>Artificial Sequence </s213>
<s220>
<s223>Oligonucleotide capable of binding specifically 
      to mecA gene or RNA derived from said gene </s223>
</s220>
</s200>
<s400> 6 
ttataatctt ttttagatac                                                 20 
</s400>
<s200>
<s210>7 </s210>
<s211>20 </s211>
<s212>DNA </s212>
<s213>Artificial Sequence </s213>
<s220>
<s223>Oligonucleotide capable of binding specifically 
      to mecA gene or RNA derived from said gene </s223>
</s220>
</s200>
<s400> 7 
atacttagtt ctttagcgat                                                 20 
</s400>
<s200>
<s210>8 </s210>
<s211>39 </s211>
<s212>DNA </s212>
<s213>Artificial Sequence </s213>
<s220>
<s223>Oligonucleotide capable of binding specifically 
      to mecA gene or RNA derived from said gene </s223>
</s220>
</s200>
<s400> 8 
cccaattttg atccatttgt tgttgatata gtcttcaga                            39 
</s400>
<s200>
<s210>9 </s210>
<s211>20 </s211>
<s212>DNA </s212>
<s213>Artificial Sequence </s213>
<s220>
<s223>Oligonucleotide capable of binding specifically 
      to mecA gene or RNA derived from said gene </s223>
</s220>
</s200>
<s400> 9 
atttttttgc gaaatcactt                                                 20 
</s400>
<s200>
<s210>10 </s210>
<s211>21 </s211>
<s212>DNA </s212>
<s213>Artificial Sequence </s213>
<s220>
<s223>Oligonucleotide capable of binding specifically 
      to mecA gene or RNA derived from said gene </s223>
</s220>
</s200>
<s400> 10 
ttttcttttt ctctattaat g                                               21 
</s400>
<s200>
<s210>11 </s210>
<s211>20 </s211>
<s212>DNA </s212>
<s213>Artificial Sequence </s213>
<s220>
<s223>Oligonucleotide capable of binding specifically 
      to mecA gene or RNA derived from said gene </s223>
</s220>
</s200>
<s400> 11 
gttagttgaa tatctttgcc                                                 20 
</s400>
<s200>
<s210>12 </s210>
<s211>20 </s211>
<s212>DNA </s212>
<s213>Artificial Sequence </s213>
<s220>
<s223>Oligonucleotide capable of binding specifically 
      to mecA gene or RNA derived from said gene </s223>
</s220>
</s200>
<s400> 12 
atttattata ttcttcgtta                                                 20 
</s400>
<s200>
<s210>13 </s210>
<s211>20 </s211>
<s212>DNA </s212>
<s213>Artificial Sequence </s213>
<s220>
<s223>Oligonucleotide capable of binding specifically 
      to mecA gene or RNA derived from said gene </s223>
</s220>
</s200>
<s400> 13 
ttctttttta tcttcggtta                                                 20 
</s400>
<s200>
<s210>14 </s210>
<s211>20 </s211>
<s212>DNA </s212>
<s213>Artificial Sequence </s213>
<s220>
<s223>Oligonucleotide capable of binding specifically 
      to mecA gene or RNA derived from said gene </s223>
</s220>
</s200>
<s400> 14 
tcattgctgt taatattttt                                                 20 
</s400>
<s200>
<s210>15 </s210>
<s211>20 </s211>
<s212>DNA </s212>
<s213>Artificial Sequence </s213>
<s220>
<s223>Oligonucleotide capable of binding specifically 
      to mecA gene or RNA derived from said gene </s223>
</s220>
</s200>
<s400> 15 
ctttgttttt cgtgtctttt                                                 20 
</s400>
<s200>
<s210>16 </s210>
<s211>20 </s211>
<s212>DNA </s212>
<s213>Artificial Sequence </s213>
<s220>
<s223>Oligonucleotide capable of binding specifically 
      to mecA gene or RNA derived from said gene </s223>
</s220>
</s200>
<s400> 16 
ttaatagatt gatattttct                                                 20 
</s400>
<s200>
<s210>17 </s210>
<s211>14 </s211>
<s212>DNA </s212>
<s213>Artificial Sequence </s213>
<s220>
<s223>Oligonucleotide capable of binding specifically 
      to mecA gene or RNA derived from said gene </s223>
</s220>
</s200>
<s400> 17 
gaaggtgtgc ttac                                                       14 
</s400>
<s200>
<s210>18 </s210>
<s211>28 </s211>
<s212>DNA </s212>
<s213>Artificial Sequence </s213>
<s220>
<s223>Primer </s223>
</s220>
</s200>
<s400> 18 
aaattgggta caagatgata ccttcgtt                                        28 
</s400>
<s200>
<s210>19 </s210>
<s211>14 </s211>
<s212>DNA </s212>
<s213>Artificial Sequence </s213>
<s220>
<s223>Primer </s223>
</s220>
</s200>
<s400> 19 
gaaggtgtgc ttac                                                       14 
</s400>
<s200>
<s210>20 </s210>
<s211>21 </s211>
<s212>DNA </s212>
<s213>Artificial Sequence </s213>
<s220>
<s223>Primer </s223>
</s220>
</s200>
<s400> 20 
ttttcttttt ctctattaat g                                               21 
</s400>
<s200>
<s210>21 </s210>
<s211>20 </s211>
<s212>DNA </s212>
<s213>Artificial Sequence </s213>
<s220>
<s223>Primer </s223>
</s220>
</s200>
<s400> 21 
gttagttgaa tatctttgcc                                                 20 
</s400>
<s200>
<s210>22 </s210>
<s211>28 </s211>
<s212>DNA </s212>
<s213>Artificial Sequence </s213>
<s220>
<s223>Primer </s223>
</s220>
</s200>
<s400> 22 
aaagaaaaaa gatggcaaag atattcaa                                        28 
</s400>
<s200>
<s210>23 </s210>
<s211>20 </s211>
<s212>DNA </s212>
<s213>Artificial Sequence </s213>
<s220>
<s223>Primer </s223>
</s220>
</s200>
<s400> 23 
ttctttttta tcttcggtta                                                 20 
</s400>
<s200>
<s210>24 </s210>
<s211>20 </s211>
<s212>DNA </s212>
<s213>Artificial Sequence </s213>
<s220>
<s223>Primer </s223>
</s220>
</s200>
<s400> 24 
tcattgctgt taatattttt                                                 20 
</s400>
<s200>
<s210>25 </s210>
<s211>28 </s211>
<s212>DNA </s212>
<s213>Artificial Sequence </s213>
<s220>
<s223>Primer </s223>
</s220>
</s200>
<s400> 25 
caactaacta ttgatgctaa agttcaaa                                        28 
</s400>
<s200>
<s210>26 </s210>
<s211>39 </s211>
<s212>DNA </s212>
<s213>Artificial Sequence </s213>
<s220>
<s223>Probe </s223>
</s220>
</s200>
<s400> 26 
cccaattttg atccatttgt tgttgatata gtcttcaga                            39 
</s400>
<s200>
<s210>27 </s210>
<s211>39 </s211>
<s212>DNA </s212>
<s213>Artificial Sequence </s213>
<s220>
<s223>Probe </s223>
</s220>
</s200>
<s400> 27 
ttttcttttt ctctattaat gtatgtgcga ttgtattgc                            39 
</s400>
<s200>
<s210>28 </s210>
<s211>39 </s211>
<s212>DNA </s212>
<s213>Artificial Sequence </s213>
<s220>
<s223>Probe </s223>
</s220>
</s200>
<s400> 28 
gttagttgaa tatctttgcc atcttttttc tttttctct                            39 
</s400>
<s200>
<s210>29 </s210>
<s211>20 </s211>
<s212>DNA </s212>
<s213>Artificial Sequence </s213>
<s220>
<s223>Primer </s223>
</s220>
</s200>
<s400> 29 
tgtttgaggg tggatagcag                                                 20 
</s400>
<s200>
<s210>30 </s210>
<s211>28 </s211>
<s212>DNA </s212>
<s213>T7 phage </s213>
<s220>
<s221>
promoter 
</s221>
<s223>Promoter sequence of T7 polymerase </s223>
</s220>
</s200>
<s400> 30 
aattctaata cgactcacta tagggaga                                        28
</s400>
</sequence-list-new-rules>
</sequence-cwu>
